stock_summary_report/__init__.py
stock_summary_report/core.py
stock_summary_report-0.1.4.dist-info/licenses/LICENSE
stock_summary_report-0.1.4.dist-info/METADATA
stock_summary_report-0.1.4.dist-info/WHEEL
stock_summary_report-0.1.4.dist-info/entry_points.txt
stock_summary_report-0.1.4.dist-info/top_level.txt
stock_summary_report-0.1.4.dist-info/RECORD
