Metadata-Version: 2.4
Name: stock_summary_report
Version: 0.1.4
Summary: Print stock flow between a date range
Home-page: https://github.com/tristanle22/inventree_stock_summary_report
Author: Tristan Le
Author-email: tristan.tuanle@gmail.com
License: MIT
Keywords: inventree plugin
Requires-Python: >=3.9
License-File: LICENSE
Dynamic: author
Dynamic: author-email
Dynamic: description
Dynamic: description-content-type
Dynamic: home-page
Dynamic: keywords
Dynamic: license
Dynamic: license-file
Dynamic: requires-python
Dynamic: summary
